CricBuzzScr/__init__.py
CricBuzzScr/match.py
cricbuzzscr-0.2.dist-info/METADATA
cricbuzzscr-0.2.dist-info/WHEEL
cricbuzzscr-0.2.dist-info/top_level.txt
cricbuzzscr-0.2.dist-info/RECORD
