Metadata-Version: 2.1
Name: cricbuzzscr
Version: 0.2
Summary: You can get the live scores from cricbuzz.com. You can also view commentary and scorecard.
Author: Sai Siddhanth S
Author-email: saisiddhanthreddy@gmail.com
Project-URL: Homepage, https://github.com/Siddhu-26/CricBuzzScr
Project-URL: Bug Tracker, https://github.com/Siddhu-26/CricBuzzScr/issues
Requires-Python: >=3.7
Requires-Dist: beautifulsoup4
